innostage/__init__.py
innostage/main.py
innostage-7.0.4.dist-info/LICENSE
innostage-7.0.4.dist-info/METADATA
innostage-7.0.4.dist-info/WHEEL
innostage-7.0.4.dist-info/top_level.txt
innostage-7.0.4.dist-info/RECORD
