Metadata-Version: 2.1
Name: innostage
Version: 7.0.4
Summary: A demo package.
Home-page: https://github.com/Neiroline/innostage
Author: Amelio
Author-email: jiznetoigra@gmail.com
Project-URL: Bug Tracker, https://github.com/Neiroline/innostage/issues
Classifier: Programming Language :: Python :: 3
Classifier: License :: OSI Approved :: MIT License
Classifier: Operating System :: OS Independent
Requires-Python: >=3.6
License-File: LICENSE
